MANIFEST.in
README.md
requirements.txt
setup.py
powerpbackend_client/__init__.py
powerpbackend_client/powerpbackend.py
powerpbackend_client.egg-info/PKG-INFO
powerpbackend_client.egg-info/SOURCES.txt
powerpbackend_client.egg-info/dependency_links.txt
powerpbackend_client.egg-info/entry_points.txt
powerpbackend_client.egg-info/pbr.json
powerpbackend_client.egg-info/requires.txt
powerpbackend_client.egg-info/top_level.txt