Metadata-Version: 1.0
Name: powerpbackend-client
Version: 0.1.3
Summary: Client of PowERP Backend
Home-page: https://gitlab.com/gisce/backend-client
Author: GISCE-TI, S.L.
Author-email: devel@gisce.net
License: MIT
Platform: UNKNOWN
